task_framework/__init__.py
task_framework/access_filter.py
task_framework/auth.py
task_framework/context.py
task_framework/dependencies.py
task_framework/errors.py
task_framework/exceptions.py
task_framework/execution.py
task_framework/framework.py
task_framework/health.py
task_framework/lb.py
task_framework/logging.py
task_framework/metrics.py
task_framework/metrics_proxy.py
task_framework/proxy.py
task_framework/proxy_registry.py
task_framework/server.py
task_framework/storage_factory.py
task_framework/thread_state.py
task_framework/version.py
task_framework/api/__init__.py
task_framework/api/admin_tasks.py
task_framework/api/artifacts.py
task_framework/api/credentials.py
task_framework/api/files.py
task_framework/api/metadata.py
task_framework/api/proxy.py
task_framework/api/proxy_admin.py
task_framework/api/proxy_discovery.py
task_framework/api/runs.py
task_framework/api/schedules.py
task_framework/api/settings.py
task_framework/api/threads.py
task_framework/api/webhooks.py
task_framework/cli/__init__.py
task_framework/cli/bootstrap.py
task_framework/cli/package.py
task_framework/cli/run.py
task_framework/delivery/__init__.py
task_framework/delivery/delivery_engine.py
task_framework/delivery/event_publisher.py
task_framework/delivery/filter.py
task_framework/delivery/payload_builder.py
task_framework/delivery/signature.py
task_framework/interfaces/__init__.py
task_framework/interfaces/database.py
task_framework/interfaces/deployment_tracker_store.py
task_framework/interfaces/idempotency.py
task_framework/interfaces/logger.py
task_framework/interfaces/scheduler.py
task_framework/interfaces/storage.py
task_framework/interfaces/task_registry_store.py
task_framework/middleware/__init__.py
task_framework/middleware/admin_auth.py
task_framework/models/__init__.py
task_framework/models/artifact.py
task_framework/models/artifact_download_response.py
task_framework/models/artifact_list_response.py
task_framework/models/artifact_query_filters.py
task_framework_py-0.0.13b0.dist-info/METADATA
task_framework_py-0.0.13b0.dist-info/WHEEL
task_framework_py-0.0.13b0.dist-info/RECORD
