Metadata-Version: 2.4
Name: task-framework-py
Version: 0.0.13b0
Summary: A Python library for building task-based workflows with scheduling, webhooks, artifact management, and observability
Project-URL: Documentation, https://github.com/Cinco-AI/task-framework-new#readme
Project-URL: Repository, https://github.com/Cinco-AI/task-framework-new
Project-URL: Issues, https://github.com/Cinco-AI/task-framework-new/issues
Project-URL: Changelog, https://github.com/Cinco-AI/task-framework-new/blob/main/CHANGELOG.md
Author: Task Framework Contributors
License: MIT
Keywords: artifacts,async,fastapi,observability,scheduling,task,webhooks,workflow
Classifier: Development Status :: 4 - Beta
Classifier: Framework :: FastAPI
Classifier: Intended Audience :: Developers
Classifier: License :: OSI Approved :: MIT License
Classifier: Operating System :: OS Independent
Classifier: Programming Language :: Python :: 3
Classifier: Programming Language :: Python :: 3.13
Classifier: Topic :: Software Development :: Libraries :: Python Modules
Classifier: Topic :: System :: Distributed Computing
Classifier: Typing :: Typed
Requires-Python: >=3.13
Requires-Dist: aiofiles>=24.1.0
Requires-Dist: aiohttp>=3.9.0
Requires-Dist: anthropic>=0.39.0
Requires-Dist: apscheduler>=3.11.0
Requires-Dist: beautifulsoup4>=4.12.0
Requires-Dist: cryptography>=43.0.0
Requires-Dist: fastapi>=0.115.0
Requires-Dist: fastmcp==2.11.0
Requires-Dist: google-generativeai>=0.8.0
Requires-Dist: httpx>=0.27.0
Requires-Dist: jsonschema>=4.23.0
Requires-Dist: markdown>=3.10
Requires-Dist: matplotlib>=3.10.7
Requires-Dist: neo4j>=6.0.3
Requires-Dist: networkx>=3.6
Requires-Dist: openai-agents>=0.5.1
Requires-Dist: openai>=1.54.0
Requires-Dist: openpyxl>=3.1.0
Requires-Dist: pdfplumber>=0.10.0
Requires-Dist: prometheus-client>=0.21.0
Requires-Dist: pydantic>=2.10.0
Requires-Dist: python-docx>=1.1.0
Requires-Dist: python-multipart>=0.0.9
Requires-Dist: pyyaml>=6.0.3
Requires-Dist: scipy>=1.11.0
Requires-Dist: structlog>=24.4.0
Requires-Dist: uvicorn[standard]>=0.32.0
Requires-Dist: xhtml2pdf>=0.2.17
Provides-Extra: dev
Requires-Dist: black>=24.8.0; extra == 'dev'
Requires-Dist: httpx>=0.27.0; extra == 'dev'
Requires-Dist: mypy>=1.13.0; extra == 'dev'
Requires-Dist: pytest-asyncio>=0.24.0; extra == 'dev'
Requires-Dist: pytest-cov>=4.1.0; extra == 'dev'
Requires-Dist: pytest>=8.3.0; extra == 'dev'
Requires-Dist: requests>=2.32.0; extra == 'dev'
Requires-Dist: ruff>=0.8.0; extra == 'dev'
Provides-Extra: elasticsearch
Requires-Dist: elasticsearch[async]>=9.0.0; extra == 'elasticsearch'
Provides-Extra: remote
Requires-Dist: aiobotocore>=2.11.0; extra == 'remote'
Requires-Dist: boto3>=1.34.0; extra == 'remote'
Requires-Dist: elasticsearch[async]>=9.0.0; extra == 'remote'
Provides-Extra: s3
Requires-Dist: aiobotocore>=2.11.0; extra == 's3'
Requires-Dist: boto3>=1.34.0; extra == 's3'
Provides-Extra: test
Requires-Dist: httpx>=0.27.0; extra == 'test'
Requires-Dist: playwright>=1.40.0; extra == 'test'
Requires-Dist: pytest-asyncio>=0.24.0; extra == 'test'
Requires-Dist: pytest-cov>=4.1.0; extra == 'test'
Requires-Dist: pytest-playwright>=0.4.0; extra == 'test'
Requires-Dist: pytest>=8.3.0; extra == 'test'
